style_transfer/__init__.py
style_transfer/cli.py
style_transfer/main.py
style_transfer/py.typed
style_transfer/libs/__init__.py
style_transfer/libs/base_transfer.py
style_transfer/libs/transfer_factory.py
style_transfer/libs/fast_photo_style_transfer/fast_photo_style_transfer.py
style_transfer/libs/fast_photo_style_transfer/gif_smoothing.py
style_transfer/libs/fast_photo_style_transfer/models.py
style_transfer/libs/fast_photo_style_transfer/photo_wct.py
style_transfer/utils/__init__.py
style_transfer/utils/downloader.py
style_transfer/utils/image_utils.py
chromasoul_style_transfer-1.0.2.dist-info/METADATA
chromasoul_style_transfer-1.0.2.dist-info/WHEEL
chromasoul_style_transfer-1.0.2.dist-info/entry_points.txt
chromasoul_style_transfer-1.0.2.dist-info/licenses/LICENSE
chromasoul_style_transfer-1.0.2.dist-info/RECORD
