Metadata-Version: 2.4
Name: chromasoul_style_transfer
Version: 1.0.2
Summary: StyleTransfer provides a suite of tools for style migration tasks.
Author-email: XIAODUOLU <lxd0705@163.com>
License-File: LICENSE
Requires-Python: >=3.12
Requires-Dist: appdirs>=1.4.4
Requires-Dist: black>=25.9.0
Requires-Dist: numpy==1.26
Requires-Dist: opencv-contrib-python>=4.11.0.86
Requires-Dist: opencv-python>=4.11.0.86
Requires-Dist: requests>=2.32.5
Requires-Dist: torch>=2.9.0
Requires-Dist: torchvision>=0.24.0
Requires-Dist: tqdm>=4.67.1
